{
  "records": [
    {
      "id": "9388f9116e014b958abe90beb427faa9",
      "category": "3. Máy Tính",
      "fields": {
        "Mã BĐ Xã": "",
        "Tên Xã": "",
        "Mã Bưu cục": "TTVH",
        "Tên Bưu cục": "Trung Tâm Vận Hành",
        "Họ và tên người sử dụng": "Cao Thành Trai",
        "Mã HRM": "00098243",
        "Bộ phận / Phòng ban": "Trung Tâm Vận Hành",
        "Mã vật tư": "",
        "Tên máy (Hostname)": "LAN-KTNV-TRAICT",
        "Loại máy": "Laptop",
        "Hãng": "Dell Inc.",
        "Model": "Latitude 3420",
        "Năm sản xuất": "",
        "Serial Number": "77WTKG3",
        "CPU": "11th Gen Intel(R) Core(TM) i5-1135G7 @ 2.40GHz",
        "RAM": "15.7 GB",
        "Ổ cứng": "942 GB",
        "Hệ điều hành": "Microsoft Windows 10 Pro 10.0.19045",
        "Office": "Microsoft Office Professional Plus 2021 - en-us",
        "Antivirus": "Windows Defender, FortiClient AntiVirus, Kaspersky Endpoint Security for Windows",
        "IP Address": "10.81.14.102",
        "MAC Address": "B4:45:06:27:96:DF"
      },
      "attachments": [],
      "createdAt": "2026-06-24T12:34:09",
      "updatedAt": "2026-06-24T12:34:09"
    },
    {
      "id": "37d3f626bbf04eada2b97c7a28f1f844",
      "category": "3. Máy Tính",
      "fields": {
        "Mã BĐ Xã": "",
        "Tên Xã": "",
        "Mã Bưu cục": "850000",
        "Tên Bưu cục": "Bưu điện Tây ninh",
        "Họ và tên người sử dụng": "Nguyễn Phước Vinh",
        "Mã HRM": "00043828",
        "Bộ phận / Phòng ban": "TTVH",
        "Mã vật tư": "",
        "Tên máy (Hostname)": "LAN-KTNV-VINHNP",
        "Loại máy": "Desktop",
        "Hãng": "Dell Inc.",
        "Model": "Vostro 3669",
        "Năm sản xuất": "",
        "Serial Number": "H5LXTK2",
        "CPU": "Intel(R) Core(TM) i3-7100 CPU @ 3.90GHz",
        "RAM": "11.9 GB",
        "Ổ cứng": "222 GB",
        "Hệ điều hành": "Microsoft Windows 10 Home 10.0.19045",
        "Office": "Microsoft Office Office 64-bit Components 2010",
        "Antivirus": "Windows Defender, FortiClient AntiVirus, Kaspersky Endpoint Security for Windows",
        "IP Address": "10.81.14.235",
        "MAC Address": "50:9A:4C:0E:2E:A8"
      },
      "attachments": [],
      "createdAt": "2026-06-25T00:30:30",
      "updatedAt": "2026-06-25T00:30:30"
    },
    {
      "id": "e30cb1be7a444a118279ba474487e44b",
      "category": "3. Máy Tính",
      "fields": {
        "Mã BĐ Xã": "",
        "Tên Xã": "",
        "Mã Bưu cục": "850000",
        "Tên Bưu cục": "BCGD P LONG AN",
        "Họ và tên người sử dụng": "TRƯƠNG HOÀNG GIANG",
        "Mã HRM": "00043997",
        "Bộ phận / Phòng ban": "GIAO DỊCH",
        "Mã vật tư": "",
        "Tên máy (Hostname)": "LAN-TAN-GDTT-49",
        "Loại máy": "Desktop",
        "Hãng": "LENOVO",
        "Model": "11T4S8YP00",
        "Năm sản xuất": "",
        "Serial Number": "GM06Z0QS",
        "CPU": "12th Gen Intel(R) Core(TM) i3-12100T",
        "RAM": "7.7 GB",
        "Ổ cứng": "253 GB",
        "Hệ điều hành": "Microsoft Windows 11 Home 10.0.22631",
        "Office": "Microsoft Office Office 64-bit Components 2010",
        "Antivirus": "Windows Defender, Kaspersky Endpoint Security for Windows",
        "IP Address": "10.81.34.49",
        "MAC Address": "9C:2D:CD:29:6B:D3"
      },
      "attachments": [],
      "createdAt": "2026-06-25T01:02:36",
      "updatedAt": "2026-06-25T01:02:36"
    },
    {
      "id": "e99702f0cb1444cdb1273a1c509decd1",
      "category": "3. Máy Tính",
      "fields": {
        "Mã BĐ Xã": "",
        "Tên Xã": "",
        "Mã Bưu cục": "850000",
        "Tên Bưu cục": "bưu điện tỉnh Tây Ninh",
        "Họ và tên người sử dụng": "Nguyễn Phạm Hồng Liên",
        "Mã HRM": "00239256",
        "Bộ phận / Phòng ban": "Phòng Tổ chức hành chính",
        "Mã vật tư": "",
        "Tên máy (Hostname)": "LAN-TCHC-L",
        "Loại máy": "Desktop",
        "Hãng": "Dell Inc.",
        "Model": "Vostro 3669",
        "Năm sản xuất": "",
        "Serial Number": "BKX62K2",
        "CPU": "Intel(R) Core(TM) i3-7100 CPU @ 3.90GHz",
        "RAM": "3.9 GB",
        "Ổ cứng": "223 GB",
        "Hệ điều hành": "Microsoft Windows 10 Home 10.0.19045",
        "Office": "Microsoft Office Office 64-bit Components 2010",
        "Antivirus": "Windows Defender, Kaspersky Endpoint Security for Windows",
        "IP Address": "10.81.14.185",
        "MAC Address": "50:9A:4C:02:B4:E8"
      },
      "attachments": [],
      "createdAt": "2026-06-25T01:32:13",
      "updatedAt": "2026-06-25T01:32:13"
    },
    {
      "id": "a0d5e327b5534346977b6ed4f6fc9309",
      "category": "3. Máy Tính",
      "fields": {
        "Mã BĐ Xã": "",
        "Tên Xã": "",
        "Mã Bưu cục": "852420",
        "Tên Bưu cục": "Bưu cục Vận Hành Khu Vực Bến Lức- Thủ Thừa",
        "Họ và tên người sử dụng": "Phan Bùi Hưng",
        "Mã HRM": "00108074",
        "Bộ phận / Phòng ban": "BCVH",
        "Mã vật tư": "",
        "Tên máy (Hostname)": "BCVHBENLUC-TBC",
        "Loại máy": "Desktop",
        "Hãng": "Dell Inc.",
        "Model": "Vostro 3653",
        "Năm sản xuất": "",
        "Serial Number": "F13N8F2",
        "CPU": "Intel(R) Core(TM) i3-6100 CPU @ 3.70GHz",
        "RAM": "7.9 GB",
        "Ổ cứng": "224 GB",
        "Hệ điều hành": "Microsoft Windows 10 Pro 10.0.19045",
        "Office": "Microsoft Office Professional Plus 2019 - en-us",
        "Antivirus": "Windows Defender, FortiClient AntiVirus",
        "IP Address": "10.81.165.95",
        "MAC Address": "F4:8E:38:A5:49:D6"
      },
      "attachments": [
        {
          "type": "laser_printer",
          "name": "Canon121/122",
          "serial": "NYMA009346"
        }
      ],
      "createdAt": "2026-06-25T05:07:24",
      "updatedAt": "2026-06-25T05:07:24"
    },
    {
      "id": "7b64166425e74586af398279fb3a664c",
      "category": "3. Máy Tính",
      "fields": {
        "Mã BĐ Xã": "",
        "Tên Xã": "",
        "Mã Bưu cục": "852420",
        "Tên Bưu cục": "Bưu cục Vận Hành Khu Vực Bến Lức- Thủ Thừa",
        "Họ và tên người sử dụng": "Phan Bùi Hưng",
        "Mã HRM": "00108074",
        "Bộ phận / Phòng ban": "BCVH",
        "Mã vật tư": "",
        "Tên máy (Hostname)": "BCVHBENLUC-TBC",
        "Loại máy": "Desktop",
        "Hãng": "Dell Inc.",
        "Model": "Vostro 3653",
        "Năm sản xuất": "",
        "Serial Number": "F13N8F2",
        "CPU": "Intel(R) Core(TM) i3-6100 CPU @ 3.70GHz",
        "RAM": "7.9 GB",
        "Ổ cứng": "224 GB",
        "Hệ điều hành": "Microsoft Windows 10 Pro 10.0.19045",
        "Office": "Microsoft Office Professional Plus 2019 - en-us",
        "Antivirus": "Windows Defender, FortiClient AntiVirus",
        "IP Address": "10.81.165.95",
        "MAC Address": "F4:8E:38:A5:49:D6"
      },
      "attachments": [
        {
          "type": "laser_printer",
          "name": "Canon121/122",
          "serial": ""
        }
      ],
      "createdAt": "2026-06-25T05:08:49",
      "updatedAt": "2026-06-25T05:08:49"
    },
    {
      "id": "d8a995ff7eca4449969ab7b85dbe2b50",
      "category": "3. Máy Tính",
      "fields": {
        "Mã BĐ Xã": "8442",
        "Tên Xã": "TÂN LẬP",
        "Mã Bưu cục": "842211",
        "Tên Bưu cục": "BĐ-VHX THẠNH BÌNH",
        "Họ và tên người sử dụng": "Nguyễn Thị Thanh Thúy",
        "Mã HRM": "00245366",
        "Bộ phận / Phòng ban": "KINH DOANH",
        "Mã vật tư": "",
        "Tên máy (Hostname)": "TNH-KT11",
        "Loại máy": "Desktop",
        "Hãng": "Dell Inc.",
        "Model": "OptiPlex 3050 AIO",
        "Năm sản xuất": "",
        "Serial Number": "GBYR9M2",
        "CPU": "Intel(R) Core(TM) i3-7100T CPU @ 3.40GHz",
        "RAM": "3.7 GB",
        "Ổ cứng": "240 GB",
        "Hệ điều hành": "Microsoft Windows 10 Home 10.0.19045",
        "Office": "Microsoft Office Office 64-bit Components 2010",
        "Antivirus": "Windows Defender, FortiClient AntiVirus",
        "IP Address": "192.168.1.2",
        "MAC Address": "BC:A8:A6:A8:53:F4"
      },
      "attachments": [
        {
          "type": "laser_printer",
          "name": "HP LASERJET P2035",
          "serial": "CNC0607315"
        }
      ],
      "createdAt": "2026-06-25T05:29:13",
      "updatedAt": "2026-06-25T05:29:13"
    }
  ]
}